ics_calendar_utils/__init__.py
ics_calendar_utils/event_processor.py
ics_calendar_utils/ics_generator.py
ronschaeffer_ics_calendar_utils-0.2.2.dist-info/LICENSE
ronschaeffer_ics_calendar_utils-0.2.2.dist-info/METADATA
ronschaeffer_ics_calendar_utils-0.2.2.dist-info/WHEEL
ronschaeffer_ics_calendar_utils-0.2.2.dist-info/RECORD
