Metadata-Version: 2.3
Name: ronschaeffer-ics-calendar-utils
Version: 0.2.2
Summary: Python utility library for generating and manipulating ICS calendar files
License: MIT
Keywords: python,ics,calendar,events
Author: ronschaeffer
Author-email: ron@ronschaeffer.com
Requires-Python: >=3.11
Classifier: Development Status :: 3 - Alpha
Classifier: Intended Audience :: Developers
Classifier: License :: OSI Approved :: MIT License
Classifier: Programming Language :: Python :: 3
Classifier: Programming Language :: Python :: 3.11
Classifier: Programming Language :: Python :: 3.12
Provides-Extra: dev
Requires-Dist: pre-commit (>=4.2.0) ; extra == "dev"
Requires-Dist: pytest (>=8.0) ; extra == "dev"
Requires-Dist: pytest-cov (>=6.2) ; extra == "dev"
Requires-Dist: python-dotenv (>=1.0)
Requires-Dist: pyyaml (>=6.0)
Requires-Dist: ruff (>=0.12) ; extra == "dev"
Project-URL: Homepage, https://github.com/ronschaeffer/ics_calendar_utils
Project-URL: Issues, https://github.com/ronschaeffer/ics_calendar_utils/issues
Project-URL: Repository, https://github.com/ronschaeffer/ics_calendar_utils.git
